addition/__init__.py
addition/add.py
shivam_addition-3.0.dist-info/METADATA
shivam_addition-3.0.dist-info/RECORD
shivam_addition-3.0.dist-info/WHEEL
shivam_addition-3.0.dist-info/top_level.txt
