Metadata-Version: 2.1
Name: shivam-addition
Version: 3.0
Summary: Math Addition
Home-page: https://www.github.com/shivamzaz/addition
Author: Shivam Gupta
Author-email: shivam.gupta712@gmail.com
License: MIT
Platform: UNKNOWN
Classifier: Development Status :: 1 - Planning
Classifier: Environment :: Plugins
Classifier: Intended Audience :: Developers
Classifier: License :: OSI Approved :: MIT License
Classifier: Natural Language :: English
Classifier: Operating System :: OS Independent
Classifier: Programming Language :: Python
Classifier: Topic :: Office/Business
